robust_toml_config/__init__.py
robust_toml_config/config.py
robust_toml_config-1.0.2.dist-info/licenses/LICENSE
robust_toml_config-1.0.2.dist-info/METADATA
robust_toml_config-1.0.2.dist-info/WHEEL
robust_toml_config-1.0.2.dist-info/top_level.txt
robust_toml_config-1.0.2.dist-info/RECORD
