Metadata-Version: 2.4
Name: robust-toml-config
Version: 1.0.2
Summary: Robust TOML configuration manager with format preservation
Home-page: https://gitee.com/wzs83241568/robust-toml-config
Author: wzs
Author-email: 83241568@qq.com
Project-URL: Bug Reports, https://gitee.com/wzs83241568/robust-toml-config/issues
Project-URL: Source, https://gitee.com/wzs83241568/robust-toml-config
Classifier: Programming Language :: Python :: 3
Classifier: License :: OSI Approved :: MIT License
Classifier: Operating System :: OS Independent
Requires-Python: >=3.7
License-File: LICENSE
Requires-Dist: tomlkit>=0.11.0
Provides-Extra: dev
Requires-Dist: pytest>=6.0; extra == "dev"
Requires-Dist: twine>=3.0; extra == "dev"
Dynamic: author
Dynamic: author-email
Dynamic: classifier
Dynamic: description
Dynamic: description-content-type
Dynamic: home-page
Dynamic: license-file
Dynamic: project-url
Dynamic: provides-extra
Dynamic: requires-dist
Dynamic: requires-python
Dynamic: summary
